investpy/__init__.py
investpy/calculos.py
investpy/dados.py
investpy/visualizacao.py
investimentpy_ara-1.0.1.dist-info/METADATA
investimentpy_ara-1.0.1.dist-info/WHEEL
investimentpy_ara-1.0.1.dist-info/top_level.txt
investimentpy_ara-1.0.1.dist-info/RECORD
